Workbook

Sheet Overview
A1: CONVVA African SME Commerce Platform
A3: Status | B3: Concept / MVP design
A4: Domain | B4: SME commerce and retail technology
A5: Role | B5: Product Business Analyst
A6: Business problem | B6: Small merchants manage products, stock and orders across social media, messaging and separate tools, creating duplication, overselling and weak fulfilment visibility.
A9: Measure | B9: Value | C9: Source
A10: Business requirements | B10: =COUNTA(Requirements!A2:A200) | C10: Requirements
A11: Must requirements | B11: =COUNTIF(Requirements!C2:C200,"Must") | C11: Requirements
A12: Should requirements | B12: =COUNTIF(Requirements!C2:C200,"Should") | C12: Requirements
A13: Functional requirements | B13: =COUNTA(Functional!A2:A200) | C13: Functional
A14: Requirements with a test | B14: =COUNTIF(Traceability!F2:F200,">0") | C14: Traceability
A15: Tests with status "Planned" | B15: =COUNTIF(UAT!F2:F200,"Planned") | C15: UAT
A16: High risks | B16: =COUNTIF(RAID!C2:C200,"High") | C16: RAID
A17: Stakeholder groups | B17: =COUNTA(Stakeholders!A2:A200) | C17: Stakeholders
A19: Counts are formulas and update when rows are added. Status values are recorded on the UAT sheet.

Sheet Objectives
A1: Objective ID | B1: Objective
A2: OBJ-01 | B2: Create one product and inventory source
A3: OBJ-02 | B3: Connect selected selling channels
A4: OBJ-03 | B4: Give every order a clear status
A5: OBJ-04 | B5: Make setup usable for SMEs

Sheet Requirements
A1: ID | B1: Requirement | C1: Priority | D1: Objective ID | E1: Objective | F1: Acceptance criterion
A2: BR-01 | B2: Maintain one product and inventory record | C2: Must | D2: OBJ-01 | E2: =IFERROR(INDEX(Objectives!$B:$B,MATCH(D2,Objectives!$A:$A,0)),"Check objective ID") | F2: All selected channels use the same source
A3: BR-02 | B3: Publish products to selected channels | C3: Must | D3: OBJ-02 | E3: =IFERROR(INDEX(Objectives!$B:$B,MATCH(D3,Objectives!$A:$A,0)),"Check objective ID") | F3: Changes appear on each selected channel
A4: BR-03 | B4: Prevent sale of unavailable stock | C4: Must | D4: OBJ-01 | E4: =IFERROR(INDEX(Objectives!$B:$B,MATCH(D4,Objectives!$A:$A,0)),"Check objective ID") | F4: Insufficient stock blocks or flags the order
A5: BR-04 | B5: Every order has status and a next action | C5: Must | D5: OBJ-03 | E5: =IFERROR(INDEX(Objectives!$B:$B,MATCH(D5,Objectives!$A:$A,0)),"Check objective ID") | F5: Merchant can identify the next step for each order
A6: BR-05 | B6: Guided setup for payment and delivery providers | C6: Must | D6: OBJ-04 | E6: =IFERROR(INDEX(Objectives!$B:$B,MATCH(D6,Objectives!$A:$A,0)),"Check objective ID") | F6: Merchant completes setup without support

Sheet Functional
A1: ID | B1: Parent BR | C1: System behaviour | D1: Business rule or validation
A2: FR-01 | B2: BR-01 | C2: Product record holds variants, price and stock | D2: Stock cannot go below zero
A3: FR-02 | B3: BR-02 | C3: Merchant selects channels per product | D3: Channel sync failure is shown on the product
A4: FR-03 | B4: BR-03 | C4: Order reserves stock for 15 minutes pending payment | D4: Unpaid reservations release automatically
A5: FR-04 | B5: BR-04 | C5: Order timeline shows payment, fulfilment and delivery states | D5: Next action displayed at the top of each order
A6: FR-05 | B6: BR-05 | C6: Setup wizard lists providers available in the merchant country | D6: Test transaction required before go-live

Sheet User Stories
A1: ID | B1: Parent BR | C1: As a | D1: I want | E1: So that | F1: Given | G1: When | H1: Then
A2: US-01 | B2: BR-03 | C2: merchant | D2: orders to reserve stock automatically | E2: I never sell what I do not have | F2: one item is left | G2: two customers order at once | H2: the second order is told the item is unavailable
A3: US-02 | B3: BR-04 | C3: merchant | D3: one timeline for each order | E3: I know what to do next | F3: an order is paid | G3: I open it | H3: the next action, Accept fulfilment, is shown first

Sheet Stakeholders
A1: Stakeholder | B1: Influence | C1: Interest | D1: Primary interest | E1: Information need | F1: Method | G1: Cadence | H1: Approach
A2: SME merchants | B2: Medium | C2: High | D2: Simple operations and sales | E2: Setup, orders, stock | F2: In-app guidance and WhatsApp support | G2: Ongoing | H2: Keep informed
A3: Customers | B3: Low | C3: High | D3: Reliable ordering | E3: Order and delivery status | F3: Notifications | G3: At each status change | H3: Keep informed
A4: Payment providers | B4: High | C4: Medium | D4: Transaction status | E4: API usage, volumes | F4: Partner review | G4: Quarterly | H4: Keep satisfied
A5: Delivery providers | B5: Medium | C5: Medium | D5: Fulfilment data | E5: Pickup and delivery events | F5: Partner integration brief | G5: At onboarding | H5: Monitor
A6: Platform admin | B6: High | C6: High | D6: Support and exception control | E6: Failed syncs, disputes | F6: Admin console | G6: Daily | H6: Manage closely

Sheet RAID
A1: ID | B1: Risk | C1: Severity | D1: Response | E1: Owner
A2: R-01 | B2: Channel stock becomes inconsistent | C2: High | D2: Single inventory source and sync alerts | E2: Product owner
A3: R-02 | B3: Failed payment appears complete | C3: High | D3: Confirmed payment states only | E3: Engineering lead
A4: R-03 | B4: Setup is too complex for merchants | C4: Medium | D4: Guided wizard and usability tests | E4: Business analyst
A5: R-04 | B5: Provider outage blocks fulfilment | C5: Medium | D5: Exception queue and fallback provider | E5: Operations

Sheet UAT
A1: Test ID | B1: Requirement | C1: Given | D1: When | E1: Then | F1: Status
A2: UAT-01 | B2: BR-01 | C2: stock changed in the catalogue | D2: channels are checked | E2: all show the new quantity | F2: Planned
A3: UAT-02 | B3: BR-02 | C3: a channel sync fails | D3: the merchant opens the product | E3: the failure and retry option show | F3: Planned
A4: UAT-03 | B4: BR-03 | C4: one item left and two orders | D4: both are placed together | E4: only one reserves stock | F4: Planned
A5: UAT-04 | B5: BR-04 | C5: a paid order | D5: the merchant opens it | E5: next action and timeline show | F5: Planned
A6: UAT-05 | B6: BR-05 | C6: a new merchant | D6: they complete the wizard | E6: a test transaction succeeds without support | F6: Planned

Sheet Traceability
A1: Requirement | B1: Objective ID | C1: Functional requirements | D1: User stories | E1: Test IDs | F1: Number of tests
A2: BR-01 | B2: =IFERROR(INDEX(Requirements!$D:$D,MATCH(A2,Requirements!$A:$A,0)),"") | C2: FR-01 | D2: None | E2: UAT-01 | F2: =COUNTIF(UAT!$B:$B,A2)
A3: BR-02 | B3: =IFERROR(INDEX(Requirements!$D:$D,MATCH(A3,Requirements!$A:$A,0)),"") | C3: FR-02 | D3: None | E3: UAT-02 | F3: =COUNTIF(UAT!$B:$B,A3)
A4: BR-03 | B4: =IFERROR(INDEX(Requirements!$D:$D,MATCH(A4,Requirements!$A:$A,0)),"") | C4: FR-03 | D4: US-01 | E4: UAT-03 | F4: =COUNTIF(UAT!$B:$B,A4)
A5: BR-04 | B5: =IFERROR(INDEX(Requirements!$D:$D,MATCH(A5,Requirements!$A:$A,0)),"") | C5: FR-04 | D5: US-02 | E5: UAT-04 | F5: =COUNTIF(UAT!$B:$B,A5)
A6: BR-05 | B6: =IFERROR(INDEX(Requirements!$D:$D,MATCH(A6,Requirements!$A:$A,0)),"") | C6: FR-05 | D6: None | E6: UAT-05 | F6: =COUNTIF(UAT!$B:$B,A6)

Sheet Data Dictionary
A1: Field | B1: Type | C1: Definition | D1: Allowed values
A2: merchant_id | B2: Text | C2: Unique merchant | D2: MER-0001 format
A3: product_id | B3: Text | C3: Unique product | D3: PRD-0001 format
A4: channel | B4: Category | C4: Sales channel | D4: Storefront, Instagram, WhatsApp, Facebook
A5: available_stock | B5: Integer | C5: Sellable quantity | D5: 0 or more
A6: order_status | B6: Category | C6: Order state | D6: Placed, Reserved, Paid, In fulfilment, Delivered, Cancelled
A7: delivery_status | B7: Category | C7: Fulfilment state | D7: Awaiting pickup, In transit, Delivered, Failed
