Workbook

Sheet Overview
A1: MyTicketSeller Event Ticketing Platform
A3: Status | B3: Live
A4: Domain | B4: Event technology and payments
A5: Role | B5: Founder, Product Owner and Business Analyst
A6: Business problem | B6: Organisers selling to Nigerian and diaspora audiences needed to take payment in more than one currency, get paid reliably and control who enters. Early builds were split across separate codebases, payment callbacks were unreliable and revenue was reported in blended currencies.
A9: Measure | B9: Value | C9: Source
A10: Business requirements | B10: =COUNTA(Requirements!A2:A200) | C10: Requirements
A11: Must requirements | B11: =COUNTIF(Requirements!C2:C200,"Must") | C11: Requirements
A12: Should requirements | B12: =COUNTIF(Requirements!C2:C200,"Should") | C12: Requirements
A13: Functional requirements | B13: =COUNTA(Functional!A2:A200) | C13: Functional
A14: Requirements with a test | B14: =COUNTIF(Traceability!F2:F200,">0") | C14: Traceability
A15: Tests with status "Released" | B15: =COUNTIF(UAT!F2:F200,"Released") | C15: UAT
A16: High risks | B16: =COUNTIF(RAID!C2:C200,"High") | C16: RAID
A17: Stakeholder groups | B17: =COUNTA(Stakeholders!A2:A200) | C17: Stakeholders
A19: Counts are formulas and update when rows are added. Status values are recorded on the UAT sheet.

Sheet Objectives
A1: Objective ID | B1: Objective
A2: OBJ-01 | B2: Take payment reliably and deliver tickets immediately
A3: OBJ-02 | B3: Report revenue, balances and payouts accurately in each currency
A4: OBJ-03 | B4: Control event access through ticket ownership, team roles and scanning
A5: OBJ-04 | B5: Protect buyers, organisers and the platform through refunds, dispute evidence and security
A6: OBJ-05 | B6: Measure marketing performance only with visitor consent

Sheet Requirements
A1: ID | B1: Requirement | C1: Priority | D1: Objective ID | E1: Objective | F1: Acceptance criterion
A2: BR-01 | B2: Confirmed payments issue tickets in the same checkout session | C2: Must | D2: OBJ-01 | E2: Take payment reliably and deliver tickets immediately | F2: Tickets are emailed once the return page verifies payment; pending orders are reconciled automatically
A3: BR-02 | B3: Revenue, wallet balances and payouts are held and shown per currency | C3: Must | D3: OBJ-02 | E3: Report revenue, balances and payouts accurately in each currency | F3: No figure sums two currencies; each event reports in its own currency
A4: BR-03 | B4: Gateway refunds cancel the ticket and notify the buyer | C4: Must | D4: OBJ-04 | E4: Protect buyers, organisers and the platform through refunds, dispute evidence and security | F4: Webhook signature is verified, the full ticket price is refunded and the ticket shows Cancelled
A5: BR-04 | B5: Organisers grant event access by role | C5: Must | D5: OBJ-03 | E5: Control event access through ticket ownership, team roles and scanning | F5: Door staff, viewer and manager roles exist; scanners can scan only events they own or are invited to
A6: BR-05 | B6: Tickets can be sent, transferred and swapped without distorting revenue | C6: Should | D6: OBJ-03 | E6: Control event access through ticket ownership, team roles and scanning | F6: A swapped ticket moves its revenue and is not counted as a new sale
A7: BR-06 | B7: Chargeback evidence is compiled from checkout records | C7: Should | D7: OBJ-04 | E7: Protect buyers, organisers and the platform through refunds, dispute evidence and security | F7: Terms consent is logged at checkout and an evidence PDF can be exported per dispute
A8: BR-07 | B8: Tracking pixels load only after consent | C8: Must | D8: OBJ-05 | E8: Measure marketing performance only with visitor consent | F8: GA4, Meta and TikTok stay blocked until accepted; purchase events carry an event_id for deduplication
A9: BR-08 | B9: Accounts, content and secrets are protected | C9: Must | D9: OBJ-04 | E9: Protect buyers, organisers and the platform through refunds, dispute evidence and security | F9: Auth endpoints are rate limited, rich text is sanitised and no secret is exposed in code or endpoints

Sheet Functional
A1: ID | B1: Parent BR | C1: System behaviour | D1: Business rule or validation
A2: FR-01 | B2: BR-01 | C2: Return page verifies payment with the gateway before showing tickets | D2: Gateway confirms paid: order completes; the webhook is a backup, not the only path
A3: FR-02 | B3: BR-01 | C3: Scheduled reconciliation re-checks orders left pending | D3: Orders for events already past are not auto-completed
A4: FR-03 | B4: BR-02 | C4: Wallet ledger and withdrawal requests held per currency | D4: Only active events count toward balance; fees shown before withdrawal
A5: FR-04 | B5: BR-02 | C5: Event currency derived from its paid ticket types | D5: A free ticket never sets the event or cart currency
A6: FR-05 | B6: BR-03 | C6: Refund handlers for Stripe and Flutterwave webhooks | D6: Invalid signature rejected; refund equals ticket price, not organiser share
A7: FR-06 | B7: BR-04 | C7: Team invitations with door staff, viewer or manager role | D7: Scan endpoint checks event ownership or active invite
A8: FR-07 | B8: BR-05 | C8: Ticket send, transfer and organiser swap | D8: Guest purchases link to an account on login by matching email
A9: FR-08 | B9: BR-06 | C9: Admin dispute-evidence view with PDF export | D9: Includes terms-consent time, reason code and the buyer's prior orders
A10: FR-09 | B10: BR-07 | C10: Consent banner controls GA4, Meta Pixel and TikTok Pixel | D10: No tracking script loads before consent is recorded
A11: FR-10 | B11: BR-08 | C11: Rate limits on auth, sanitised rich text and security headers | D11: App refuses to start in production without a JWT secret

Sheet User Stories
A1: ID | B1: Parent BR | C1: As a | D1: I want | E1: So that | F1: Given | G1: When | H1: Then
A2: US-01 | B2: BR-01 | C2: a ticket buyer | D2: my tickets the moment my payment succeeds | E2: I never pay twice because the page said it failed | F2: my card has been charged | G2: I return to the site | H2: my order shows paid and the tickets are in my inbox
A3: US-02 | B3: BR-02 | C3: an organiser selling in naira and pounds | D3: to see earnings in each currency separately | E3: I know exactly what I can withdraw | F3: an event has sales in GBP | G3: I open my wallet | H3: the GBP balance is shown on its own, with fees itemised
A4: US-03 | B4: BR-04 | C4: an organiser | D4: to invite door staff who can only scan my event | E4: I do not have to share my login | F4: I invite a person as door staff | G4: they sign in and scan | H4: they can scan my event and cannot see earnings

Sheet Stakeholders
A1: Stakeholder | B1: Influence | C1: Interest | D1: Primary interest | E1: Information need | F1: Method | G1: Cadence | H1: Approach
A2: Event organisers | B2: High | C2: High | D2: Payouts, sales visibility, door control | E2: Earnings rules, payout timing | F2: Dashboard messages and release notes | G2: Per release | H2: Manage closely
A3: Ticket buyers | B3: Low | C3: High | D3: Fast checkout, instant tickets, refunds | E3: Order status, refund outcome | F3: Transactional email | G3: Per order | H3: Keep informed
A4: Door and scanning staff | B4: Low | C4: Medium | D4: Simple, fast scanning | E4: Their role and event | F4: Invite email and in-app guidance | G4: Per event | H4: Keep informed
A5: Platform admin and finance | B5: High | C5: High | D5: Accurate revenue, withdrawals, disputes | E5: Currency totals, pending approvals | F5: Admin panel | G5: Daily | H5: Manage closely
A6: Contract developers | B6: High | C6: Medium | D6: Clear, testable requirements | E6: Acceptance criteria and priorities | F6: Backlog walkthrough | G6: Each sprint | H6: Keep satisfied
A7: Payment providers | B7: Medium | C7: Low | D7: Correct integration and dispute handling | E7: Webhook and dispute data | F7: Provider dashboards | G7: As needed | H7: Monitor

Sheet RAID
A1: ID | B1: Risk | C1: Severity | D1: Response | E1: Owner
A2: R-01 | B2: Payment callbacks arrive late or not at all | C2: High | D2: Verify on return page and reconcile pending orders | E2: Product owner
A3: R-02 | B3: Currency errors misstate organiser earnings | C3: High | D3: Per-currency ledger and display rules | E3: Product owner
A4: R-03 | B4: Security gaps left by rapid early builds | C4: High | D4: Audit: remove debug endpoints, move secrets, rate limit auth | E4: Product owner
A5: R-04 | B5: Chargebacks lost without evidence | C5: Medium | D5: Log terms consent and export evidence per dispute | E5: Admin and finance
A6: R-05 | B6: Dependence on individual contract developers | C6: Medium | D6: Single codebase, written requirements and owner-led fixes | E6: Product owner

Sheet UAT
A1: Test ID | B1: Requirement | C1: Given | D1: When | E1: Then | F1: Status
A2: UAT-01 | B2: BR-01 | C2: a buyer whose payment succeeded but whose webhook is delayed | D2: they land on the return page | E2: the order is verified and tickets are emailed | F2: Released
A3: UAT-02 | B3: BR-01 | C3: an order left pending for a future event | D3: reconciliation runs | E3: a paid order completes and an unpaid one stays pending | F3: Released
A4: UAT-03 | B4: BR-02 | C4: an event with naira and pound sales | D4: the organiser opens the wallet | E4: each currency shows its own balance | F4: Released
A5: UAT-04 | B5: BR-03 | C5: a refund issued in Stripe | D5: the webhook arrives | E5: the ticket is cancelled and the buyer is emailed | F5: Released
A6: UAT-05 | B6: BR-04 | C6: door staff invited to event A | D6: they scan a ticket for event B | E6: the scan is refused | F6: Released
A7: UAT-06 | B7: BR-05 | C7: an organiser swaps a sold ticket | D7: revenue is recalculated | E7: the total is unchanged and no new sale appears | F7: Released
A8: UAT-07 | B8: BR-06 | C8: a chargeback on a completed order | D8: admin exports evidence | E8: the PDF shows consent time, reason code and prior orders | F8: Released
A9: UAT-08 | B9: BR-07 | C9: a first-time visitor | D9: they have not accepted cookies | E9: no GA4, Meta or TikTok request is sent | F9: Released

Sheet Traceability
A1: Requirement | B1: Objective ID | C1: Functional requirements | D1: User stories | E1: Test IDs | F1: Number of tests
A2: BR-01 | B2: =IFERROR(INDEX(Requirements!$D:$D,MATCH(A2,Requirements!$A:$A,0)),"") | C2: FR-01, FR-02 | D2: US-01 | E2: UAT-01, UAT-02 | F2: =COUNTIF(UAT!$B:$B,A2)
A3: BR-02 | B3: =IFERROR(INDEX(Requirements!$D:$D,MATCH(A3,Requirements!$A:$A,0)),"") | C3: FR-03, FR-04 | D3: US-02 | E3: UAT-03 | F3: =COUNTIF(UAT!$B:$B,A3)
A4: BR-03 | B4: =IFERROR(INDEX(Requirements!$D:$D,MATCH(A4,Requirements!$A:$A,0)),"") | C4: FR-05 | D4: None | E4: UAT-04 | F4: =COUNTIF(UAT!$B:$B,A4)
A5: BR-04 | B5: =IFERROR(INDEX(Requirements!$D:$D,MATCH(A5,Requirements!$A:$A,0)),"") | C5: FR-06 | D5: US-03 | E5: UAT-05 | F5: =COUNTIF(UAT!$B:$B,A5)
A6: BR-05 | B6: =IFERROR(INDEX(Requirements!$D:$D,MATCH(A6,Requirements!$A:$A,0)),"") | C6: FR-07 | D6: None | E6: UAT-06 | F6: =COUNTIF(UAT!$B:$B,A6)
A7: BR-06 | B7: =IFERROR(INDEX(Requirements!$D:$D,MATCH(A7,Requirements!$A:$A,0)),"") | C7: FR-08 | D7: None | E7: UAT-07 | F7: =COUNTIF(UAT!$B:$B,A7)
A8: BR-07 | B8: =IFERROR(INDEX(Requirements!$D:$D,MATCH(A8,Requirements!$A:$A,0)),"") | C8: FR-09 | D8: None | E8: UAT-08 | F8: =COUNTIF(UAT!$B:$B,A8)
A9: BR-08 | B9: =IFERROR(INDEX(Requirements!$D:$D,MATCH(A9,Requirements!$A:$A,0)),"") | C9: FR-10 | D9: None | E9: None | F9: =COUNTIF(UAT!$B:$B,A9)

Sheet Data Dictionary
A1: Field | B1: Type | C1: Definition | D1: Allowed values
A2: order_id | B2: Text | C2: Unique ticket purchase | D2: Gateway reference plus internal ID
A3: payment_status | B3: Category | C3: State of the purchase | D3: Pending, Completed, Failed, Refunded
A4: currency | B4: Category | C4: Currency of the event and sale | D4: NGN, GBP, USD, EUR and others enabled
A5: ticket_status | B5: Category | C5: State of an issued ticket | D5: Active, Transferred, Cancelled, Scanned
A6: team_role | B6: Category | C6: Access granted to a team member | D6: door_staff, viewer, manager
A7: tos_accepted_at | B7: Datetime | C7: When the buyer accepted the terms | D7: ISO 8601
A8: scan_result | B8: Category | C8: Outcome of a scan | D8: Admitted, Duplicate, Invalid, Not your event
